{"user": {"description": "Just a Homie-G tryna", "following": false, "profile_image_url": "http://pbs.twimg.com/profile_images/505180298171404288/WnZfwiu7_normal.jpeg", "verified": false, "listed_count": 0, "location": "", "default_profile_image": false, "profile_sidebar_fill_color": "80054C", "time_zone": "Quito", "id": 328678995, "is_translation_enabled": false, "protected": false, "name": "Aerin Hickey", "profile_image_url_https": "https://pbs.twimg.com/profile_images/505180298171404288/WnZfwiu7_normal.jpeg", "profile_sidebar_border_color": "D95E74", "profile_background_image_url": "http://pbs.twimg.com/profile_background_images/341138281/TwitterLayout_Template.br.jpg", "geo_enabled": false, "default_profile": false, "profile_background_image_url_https": "https://pbs.twimg.com/profile_background_images/341138281/TwitterLayout_Template.br.jpg", "lang": "en", "is_translator": false, "friends_count": 277, "follow_request_sent": false, "url": null, "profile_link_color": "D95E74", "statuses_count": 4463, "favourites_count": 4781, "entities": {"description": {"urls": []}}, "profile_use_background_image": true, "created_at": "Sun Jul 03 20:42:41 +0000 2011", "profile_background_color": "FFC501", "profile_background_tile": false, "profile_text_color": "999999", "notifications": false, "utc_offset": -18000, "screen_name": "a_hickk", "profile_banner_url": "https://pbs.twimg.com/profile_banners/328678995/1407903646", "contributors_enabled": false, "id_str": "328678995", "followers_count": 353}, "in_reply_to_status_id_str": null, "favorite_count": 0, "retweet_count": 0, "in_reply_to_user_id": null, "id": 100320665126711296, "truncated": false, "in_reply_to_screen_name": null, "coordinates": null, "geo": null, "in_reply_to_status_id": null, "source": "<a href=\"http://twitter.com\" rel=\"nofollow\">Twitter Web Client</a>", "entities": {"urls": [], "hashtags": [], "symbols": [], "user_mentions": []}, "retweeted": false, "favorited": false, "created_at": "Sun Aug 07 21:41:25 +0000 2011", "id_str": "100320665126711296", "place": null, "in_reply_to_user_id_str": null, "lang": "en", "contributors": null, "text": "@VictoriaMiringu clemson sweatshirt came in today, got new uggs and got a couple pairs of 7 jeans....im ready but winter wont be the same."}