{"user": {"description": "'In Desolate Times' Re-Release Aug 8th'\r\nOfficial Atlas&i Twitter. Follow @Atlas_Jarrod @Atlas_matt, @Atlas_rob, @Atlas_josh, @Atlas_christian, @Atlas_owen", "following": false, "profile_image_url": "http://pbs.twimg.com/profile_images/1456575421/ATLAS_PAC_SHOT__Small.jpg_normal.jpg", "verified": false, "listed_count": 4, "location": "", "default_profile_image": false, "profile_sidebar_fill_color": "252429", "time_zone": "London", "id": 43099065, "is_translation_enabled": false, "protected": false, "name": "Atlas&i", "profile_image_url_https": "https://pbs.twimg.com/profile_images/1456575421/ATLAS_PAC_SHOT__Small.jpg_normal.jpg", "profile_sidebar_border_color": "181A1E", "profile_background_image_url": "http://abs.twimg.com/images/themes/theme9/bg.gif", "geo_enabled": false, "default_profile": false, "profile_background_image_url_https": "https://abs.twimg.com/images/themes/theme9/bg.gif", "lang": "en", "is_translator": false, "friends_count": 81, "follow_request_sent": false, "url": "http://t.co/iFxtgHDaPy", "profile_link_color": "2FC2EF", "statuses_count": 852, "favourites_count": 6, "entities": {"description": {"urls": []}, "url": {"urls": [{"url": "http://t.co/iFxtgHDaPy", "display_url": "facebook.com/atlasandi", "expanded_url": "http://www.facebook.com/atlasandi", "indices": [0, 22]}]}}, "profile_use_background_image": true, "created_at": "Thu May 28 12:27:46 +0000 2009", "profile_background_color": "1A1B1F", "profile_background_tile": false, "profile_text_color": "666666", "notifications": false, "utc_offset": 3600, "screen_name": "Atlasandiband", "contributors_enabled": false, "id_str": "43099065", "followers_count": 399}, "in_reply_to_status_id_str": null, "favorite_count": 0, "retweet_count": 4, "in_reply_to_user_id": null, "id": 100488964372307968, "truncated": false, "in_reply_to_screen_name": null, "coordinates": null, "geo": null, "in_reply_to_status_id": null, "source": "<a href=\"http://twitter.com\" rel=\"nofollow\">Twitter Web Client</a>", "entities": {"urls": [], "hashtags": [], "symbols": [], "user_mentions": []}, "retweeted": false, "favorited": false, "created_at": "Mon Aug 08 08:50:10 +0000 2011", "id_str": "100488964372307968", "place": null, "in_reply_to_user_id_str": null, "lang": "en", "contributors": null, "text": "The re-release of 'In Desolate Times' is available WORLDWIDE TODAY! Including BONUS TRACKS. Grab a copy and let us know what you think!"}