{"user": {"description": "Gowanus is amazing and people should know! Experience everything this small BK neighborhood has to offer. We promise you won't be disapointed..GOwanUS!", "following": false, "profile_image_url": "http://pbs.twimg.com/profile_images/1477870963/tumblr_ll40vkBhsQ1qb0fx9o1_500_normal.jpg", "verified": false, "listed_count": 4, "location": "Brooklyn, NY", "default_profile_image": false, "profile_sidebar_fill_color": "C0DFEC", "time_zone": "Quito", "id": 347311370, "is_translation_enabled": false, "protected": false, "name": "Brooklyn Gowanus", "profile_image_url_https": "https://pbs.twimg.com/profile_images/1477870963/tumblr_ll40vkBhsQ1qb0fx9o1_500_normal.jpg", "profile_sidebar_border_color": "A8C7F7", "profile_background_image_url": "http://abs.twimg.com/images/themes/theme15/bg.png", "geo_enabled": false, "default_profile": false, "profile_background_image_url_https": "https://abs.twimg.com/images/themes/theme15/bg.png", "lang": "en", "is_translator": false, "friends_count": 18, "follow_request_sent": false, "url": null, "profile_link_color": "0084B4", "statuses_count": 12, "favourites_count": 0, "entities": {"description": {"urls": []}}, "profile_use_background_image": true, "created_at": "Tue Aug 02 16:09:15 +0000 2011", "profile_background_color": "022330", "profile_background_tile": false, "profile_text_color": "333333", "notifications": false, "utc_offset": -18000, "screen_name": "GOwanUS311", "contributors_enabled": false, "id_str": "347311370", "followers_count": 47}, "in_reply_to_status_id_str": null, "favorite_count": 0, "retweet_count": 0, "in_reply_to_user_id": null, "id": 100606422827544576, "truncated": false, "in_reply_to_screen_name": null, "coordinates": null, "geo": null, "in_reply_to_status_id": null, "source": "<a href=\"http://twitter.com\" rel=\"nofollow\">Twitter Web Client</a>", "entities": {"urls": [], "hashtags": [], "symbols": [], "user_mentions": []}, "retweeted": false, "favorited": false, "created_at": "Mon Aug 08 16:36:55 +0000 2011", "id_str": "100606422827544576", "place": null, "in_reply_to_user_id_str": null, "lang": "en", "contributors": null, "text": "F-Train was messed up again today between York and Carroll St....what's going on MTA???? GET IT TOGETHER!!!"}