{"user": {"description": "Stay At Home Dad. Jukebox Romeo. Knife Thrower. Photographic Explorer. Lazy Writer.", "following": false, "profile_image_url": "http://pbs.twimg.com/profile_images/478716382268231682/sswKyK6W_normal.jpeg", "verified": false, "listed_count": 4, "location": "Corner of Michigan & Trumbull", "default_profile_image": false, "profile_sidebar_fill_color": "C0DFEC", "time_zone": "Central Time (US & Canada)", "id": 45143149, "is_translation_enabled": false, "protected": false, "name": "Kyle Kastraba", "profile_image_url_https": "https://pbs.twimg.com/profile_images/478716382268231682/sswKyK6W_normal.jpeg", "profile_sidebar_border_color": "A8C7F7", "profile_background_image_url": "http://abs.twimg.com/images/themes/theme15/bg.png", "geo_enabled": false, "default_profile": false, "profile_background_image_url_https": "https://abs.twimg.com/images/themes/theme15/bg.png", "lang": "en", "is_translator": false, "friends_count": 350, "follow_request_sent": false, "url": "http://t.co/vjNoKMdAGl", "profile_link_color": "0084B4", "statuses_count": 5316, "favourites_count": 1324, "entities": {"description": {"urls": []}, "url": {"urls": [{"url": "http://t.co/vjNoKMdAGl", "display_url": "kylekastraba.wordpress.com", "expanded_url": "http://kylekastraba.wordpress.com", "indices": [0, 22]}]}}, "profile_use_background_image": true, "created_at": "Sat Jun 06 14:53:29 +0000 2009", "profile_background_color": "022330", "profile_background_tile": false, "profile_text_color": "333333", "notifications": false, "utc_offset": -18000, "screen_name": "hotwaterkyle", "profile_banner_url": "https://pbs.twimg.com/profile_banners/45143149/1402970480", "contributors_enabled": false, "id_str": "45143149", "followers_count": 153}, "in_reply_to_status_id_str": "100757915958382593", "favorite_count": 0, "retweet_count": 0, "in_reply_to_user_id": 7796072, "id": 101060707134619648, "truncated": false, "in_reply_to_screen_name": "andrewsikora", "coordinates": null, "geo": null, "in_reply_to_status_id": 100757915958382593, "source": "<a href=\"http://twitter.com/download/iphone\" rel=\"nofollow\">Twitter for iPhone</a>", "entities": {"urls": [], "hashtags": [], "symbols": [], "user_mentions": [{"screen_name": "andrewsikora", "indices": [0, 13], "id": 7796072, "id_str": "7796072", "name": "andrewsikora"}]}, "retweeted": false, "favorited": false, "created_at": "Tue Aug 09 22:42:04 +0000 2011", "id_str": "101060707134619648", "place": null, "in_reply_to_user_id_str": "7796072", "lang": "en", "contributors": null, "text": "@andrewsikora The Tigers know it's a big game as well: resting Martinez & Alburquerque Monday and bumping Verlander."}