{"user": {"description": "Do you know what really sucks? To love a person, 'til you destroy yourself.", "following": false, "profile_image_url": "http://pbs.twimg.com/profile_images/449138583149215744/WEZB0AbH_normal.jpeg", "verified": false, "listed_count": 21, "location": "Milky Way-Solar System-Earth", "default_profile_image": false, "profile_sidebar_fill_color": "E5507E", "time_zone": "Rome", "id": 299641358, "is_translation_enabled": false, "protected": false, "name": "suicidal.", "profile_image_url_https": "https://pbs.twimg.com/profile_images/449138583149215744/WEZB0AbH_normal.jpeg", "profile_sidebar_border_color": "FFFFFF", "profile_background_image_url": "http://pbs.twimg.com/profile_background_images/724830383/9c92c61ad0fc14c29d7f3a86dda5db59.jpeg", "geo_enabled": true, "default_profile": false, "profile_background_image_url_https": "https://pbs.twimg.com/profile_background_images/724830383/9c92c61ad0fc14c29d7f3a86dda5db59.jpeg", "lang": "en", "is_translator": false, "friends_count": 213, "follow_request_sent": false, "url": "http://t.co/a46KTOalOc", "profile_link_color": "FFDD00", "statuses_count": 12442, "favourites_count": 276, "entities": {"description": {"urls": []}, "url": {"urls": [{"url": "http://t.co/a46KTOalOc", "display_url": "facebook.com/AmyChesterfiel\u2026", "expanded_url": "http://www.facebook.com/AmyChesterfieldArt", "indices": [0, 22]}]}}, "profile_use_background_image": true, "created_at": "Mon May 16 13:05:55 +0000 2011", "profile_background_color": "FFC533", "profile_background_tile": true, "profile_text_color": "362720", "notifications": false, "utc_offset": 7200, "screen_name": "AmyChesterfield", "profile_banner_url": "https://pbs.twimg.com/profile_banners/299641358/1397319583", "contributors_enabled": false, "id_str": "299641358", "followers_count": 464}, "in_reply_to_status_id_str": null, "favorite_count": 0, "retweet_count": 0, "in_reply_to_user_id": null, "id": 103322649186410496, "truncated": false, "in_reply_to_screen_name": null, "coordinates": null, "geo": null, "in_reply_to_status_id": null, "source": "<a href=\"http://twitter.com\" rel=\"nofollow\">Twitter Web Client</a>", "entities": {"urls": [], "hashtags": [], "symbols": [], "user_mentions": []}, "retweeted": false, "favorited": false, "created_at": "Tue Aug 16 04:30:13 +0000 2011", "id_str": "103322649186410496", "place": null, "in_reply_to_user_id_str": null, "lang": "en", "contributors": null, "text": "Today is My Birthday,the anniversary of the death of Elvis Presley and the birthday of Madonna,I wonder if I'll be famous...I=No Talent |="}