{"user": {"description": "A Hopeless Romantic Professional Football Player/Model.. http://t.co/ydmpc79gnO NFL on my MInd. CEO of @Star_PowerEnt", "following": false, "profile_image_url": "http://pbs.twimg.com/profile_images/491988489588600832/R39PjnRM_normal.jpeg", "verified": false, "listed_count": 15, "location": " ATL", "default_profile_image": false, "profile_sidebar_fill_color": "EFEFEF", "time_zone": "Mountain Time (US & Canada)", "id": 67215245, "is_translation_enabled": false, "protected": false, "name": "Chris Wilson", "profile_image_url_https": "https://pbs.twimg.com/profile_images/491988489588600832/R39PjnRM_normal.jpeg", "profile_sidebar_border_color": "000000", "profile_background_image_url": "http://pbs.twimg.com/profile_background_images/665752197/09972c15ef8f8d56593430940116acd8.jpeg", "geo_enabled": true, "default_profile": false, "profile_background_image_url_https": "https://pbs.twimg.com/profile_background_images/665752197/09972c15ef8f8d56593430940116acd8.jpeg", "lang": "en", "is_translator": false, "friends_count": 1368, "follow_request_sent": false, "url": "http://t.co/R4GBVbaZoG", "profile_link_color": "DB250D", "statuses_count": 47414, "favourites_count": 913, "entities": {"description": {"urls": [{"url": "http://t.co/ydmpc79gnO", "display_url": "m.youtube.com/watch?v=yYPr06\u2026", "expanded_url": "http://m.youtube.com/watch?v=yYPr06MmTxA", "indices": [57, 79]}]}, "url": {"urls": [{"url": "http://t.co/R4GBVbaZoG", "display_url": "instagram.com/ChristhemodelW\u2026", "expanded_url": "http://instagram.com/ChristhemodelWilson", "indices": [0, 22]}]}}, "profile_use_background_image": true, "created_at": "Thu Aug 20 03:28:39 +0000 2009", "profile_background_color": "0F0000", "profile_background_tile": true, "profile_text_color": "F56200", "notifications": false, "utc_offset": -21600, "screen_name": "Chris__Wilson", "profile_banner_url": "https://pbs.twimg.com/profile_banners/67215245/1348447222", "contributors_enabled": false, "id_str": "67215245", "followers_count": 2434}, "in_reply_to_status_id_str": null, "favorite_count": 0, "retweet_count": 0, "in_reply_to_user_id": null, "id": 111507943047954433, "truncated": false, "in_reply_to_screen_name": null, "coordinates": null, "geo": null, "in_reply_to_status_id": null, "source": "<a href=\"http://twitter.com\" rel=\"nofollow\">Twitter Web Client</a>", "entities": {"urls": [], "hashtags": [], "symbols": [], "user_mentions": []}, "retweeted": false, "favorited": false, "created_at": "Wed Sep 07 18:35:40 +0000 2011", "id_str": "111507943047954433", "place": null, "in_reply_to_user_id_str": null, "lang": "en", "contributors": null, "text": "wrapping up this Jersey shore commercial today. Fist Pumping all day"}