{"user": {"description": "Cute as cheese - Binh Lyn Nguyen", "following": false, "profile_image_url": "http://pbs.twimg.com/profile_images/511655053942587392/R5gj2mLZ_normal.jpeg", "verified": false, "listed_count": 12, "location": "New Jersey, Garden State", "default_profile_image": false, "profile_sidebar_fill_color": "7AC3EE", "time_zone": null, "id": 298159041, "is_translation_enabled": false, "protected": false, "name": "Sam Girod", "profile_image_url_https": "https://pbs.twimg.com/profile_images/511655053942587392/R5gj2mLZ_normal.jpeg", "profile_sidebar_border_color": "65B0DA", "profile_background_image_url": "http://abs.twimg.com/images/themes/theme10/bg.gif", "geo_enabled": true, "default_profile": false, "profile_background_image_url_https": "https://abs.twimg.com/images/themes/theme10/bg.gif", "lang": "en", "is_translator": false, "friends_count": 677, "follow_request_sent": false, "url": "http://t.co/7fNHPHf571", "profile_link_color": "FF0000", "statuses_count": 48860, "favourites_count": 820, "entities": {"description": {"urls": []}, "url": {"urls": [{"url": "http://t.co/7fNHPHf571", "display_url": "SamanthaGirod.tumblr.com", "expanded_url": "http://SamanthaGirod.tumblr.com", "indices": [0, 22]}]}}, "profile_use_background_image": true, "created_at": "Fri May 13 20:29:12 +0000 2011", "profile_background_color": "642D8B", "profile_background_tile": true, "profile_text_color": "3D1957", "notifications": false, "utc_offset": null, "screen_name": "SamanthaGirod", "profile_banner_url": "https://pbs.twimg.com/profile_banners/298159041/1409534971", "contributors_enabled": false, "id_str": "298159041", "followers_count": 1159}, "in_reply_to_status_id_str": null, "favorite_count": 0, "retweet_count": 0, "in_reply_to_user_id": null, "id": 236838723973677057, "truncated": false, "in_reply_to_screen_name": null, "coordinates": null, "geo": null, "in_reply_to_status_id": null, "source": "<a href=\"http://twitter.com/download/iphone\" rel=\"nofollow\">Twitter for iPhone</a>", "entities": {"urls": [], "hashtags": [], "symbols": [], "user_mentions": []}, "retweeted": false, "favorited": false, "created_at": "Sat Aug 18 14:55:26 +0000 2012", "id_str": "236838723973677057", "place": null, "in_reply_to_user_id_str": null, "lang": "en", "contributors": null, "text": "Okay. My sister is freaking out because Allstar isn't playing at the Wildwood Show tomorrow LMFAOOOO!"}