{"user": {"description": "", "following": false, "profile_image_url": "http://pbs.twimg.com/profile_images/515613937866649600/z2RsVHCF_normal.jpeg", "verified": false, "listed_count": 0, "location": "", "default_profile_image": false, "profile_sidebar_fill_color": "EFEFEF", "time_zone": "Atlantic Time (Canada)", "id": 631393623, "is_translation_enabled": false, "protected": false, "name": "N.", "profile_image_url_https": "https://pbs.twimg.com/profile_images/515613937866649600/z2RsVHCF_normal.jpeg", "profile_sidebar_border_color": "EEEEEE", "profile_background_image_url": "http://abs.twimg.com/images/themes/theme14/bg.gif", "geo_enabled": true, "default_profile": false, "profile_background_image_url_https": "https://abs.twimg.com/images/themes/theme14/bg.gif", "lang": "en", "is_translator": false, "friends_count": 565, "follow_request_sent": false, "url": null, "profile_link_color": "009999", "statuses_count": 37461, "favourites_count": 6301, "entities": {"description": {"urls": []}}, "profile_use_background_image": true, "created_at": "Mon Jul 09 18:32:28 +0000 2012", "profile_background_color": "131516", "profile_background_tile": true, "profile_text_color": "333333", "notifications": false, "utc_offset": -10800, "screen_name": "__nmx3", "contributors_enabled": false, "id_str": "631393623", "followers_count": 834}, "in_reply_to_status_id_str": null, "favorite_count": 0, "retweet_count": 1, "in_reply_to_user_id": null, "id": 246986186604806145, "truncated": false, "in_reply_to_screen_name": null, "coordinates": null, "geo": null, "in_reply_to_status_id": null, "source": "<a href=\"http://twitter.com\" rel=\"nofollow\">Twitter Web Client</a>", "entities": {"urls": [], "hashtags": [], "symbols": [], "user_mentions": []}, "retweeted": false, "favorited": false, "created_at": "Sat Sep 15 14:57:50 +0000 2012", "id_str": "246986186604806145", "place": null, "in_reply_to_user_id_str": null, "lang": "en", "contributors": null, "text": "hopefully going to go see Romeo Santos with Catherine on december WOOT WOOT :D &lt;3,&lt;3"}