{"user": {"description": "Ummm so yea...,", "following": false, "profile_image_url": "http://pbs.twimg.com/profile_images/378800000191948719/4091b46db5ec3e0d729a58845d6fb828_normal.jpeg", "verified": false, "listed_count": 1, "location": "Milwaukee", "default_profile_image": false, "profile_sidebar_fill_color": "EFEFEF", "time_zone": "Central Time (US & Canada)", "id": 161479186, "is_translation_enabled": false, "protected": false, "name": "Carlos Danger ", "profile_image_url_https": "https://pbs.twimg.com/profile_images/378800000191948719/4091b46db5ec3e0d729a58845d6fb828_normal.jpeg", "profile_sidebar_border_color": "FFFFFF", "profile_background_image_url": "http://pbs.twimg.com/profile_background_images/611251873/60ccx1qmugd6k97mdq17.jpeg", "geo_enabled": true, "default_profile": false, "profile_background_image_url_https": "https://pbs.twimg.com/profile_background_images/611251873/60ccx1qmugd6k97mdq17.jpeg", "lang": "en", "is_translator": false, "friends_count": 138, "follow_request_sent": false, "url": "http://t.co/Gth0G7Y6J7", "profile_link_color": "50F50E", "statuses_count": 5525, "favourites_count": 126, "entities": {"description": {"urls": []}, "url": {"urls": [{"url": "http://t.co/Gth0G7Y6J7", "display_url": "facebook.com/%252525252523!\u2026", "expanded_url": "http://www.facebook.com/%252525252523!/sodumb", "indices": [0, 22]}]}}, "profile_use_background_image": true, "created_at": "Wed Jun 30 23:41:34 +0000 2010", "profile_background_color": "DBD2DB", "profile_background_tile": true, "profile_text_color": "333333", "notifications": false, "utc_offset": -18000, "screen_name": "igorance", "profile_banner_url": "https://pbs.twimg.com/profile_banners/161479186/1376859217", "contributors_enabled": false, "id_str": "161479186", "followers_count": 150}, "in_reply_to_status_id_str": null, "favorite_count": 0, "retweet_count": 0, "in_reply_to_user_id": null, "id": 247123100339150848, "truncated": false, "possibly_sensitive": false, "in_reply_to_screen_name": null, "coordinates": null, "geo": null, "in_reply_to_status_id": null, "source": "<a href=\"http://www.apple.com\" rel=\"nofollow\">iOS</a>", "entities": {"urls": [{"url": "http://t.co/CVb3RIxS", "display_url": "road.ie/therave", "expanded_url": "http://road.ie/therave", "indices": [109, 129]}], "hashtags": [], "symbols": [], "user_mentions": []}, "retweeted": false, "favorited": false, "created_at": "Sun Sep 16 00:01:53 +0000 2012", "id_str": "247123100339150848", "place": null, "in_reply_to_user_id_str": null, "lang": "en", "contributors": null, "text": "I liked 'Kendrick Lamar - The Rave / Eagles Club - September 22, 2012 ...' in the The Rave / Eagles Club App http://t.co/CVb3RIxS"}