{"user": {"description": "#IG:Im_Mr_Smith College Grad C/o 2014", "following": false, "profile_image_url": "http://pbs.twimg.com/profile_images/496864864120635392/_sAXvro9_normal.jpeg", "verified": false, "listed_count": 4, "location": "MIL-TPA", "default_profile_image": false, "profile_sidebar_fill_color": "EFEFEF", "time_zone": "Mountain Time (US & Canada)", "id": 238001932, "is_translation_enabled": false, "protected": false, "name": "414 To 813", "profile_image_url_https": "https://pbs.twimg.com/profile_images/496864864120635392/_sAXvro9_normal.jpeg", "profile_sidebar_border_color": "EEEEEE", "profile_background_image_url": "http://abs.twimg.com/images/themes/theme14/bg.gif", "geo_enabled": true, "default_profile": false, "profile_background_image_url_https": "https://abs.twimg.com/images/themes/theme14/bg.gif", "lang": "en", "is_translator": false, "friends_count": 1230, "follow_request_sent": false, "url": null, "profile_link_color": "009999", "statuses_count": 42363, "favourites_count": 241, "entities": {"description": {"urls": []}}, "profile_use_background_image": true, "created_at": "Fri Jan 14 03:56:43 +0000 2011", "profile_background_color": "131516", "profile_background_tile": true, "profile_text_color": "333333", "notifications": false, "utc_offset": -21600, "screen_name": "__RellGotti__", "profile_banner_url": "https://pbs.twimg.com/profile_banners/238001932/1374424703", "contributors_enabled": false, "id_str": "238001932", "followers_count": 1006}, "in_reply_to_status_id_str": "249325009313603584", "favorite_count": 0, "retweet_count": 0, "in_reply_to_user_id": 25015718, "id": 249325734475214848, "truncated": false, "in_reply_to_screen_name": "tobias31", "coordinates": null, "geo": null, "in_reply_to_status_id": 249325009313603584, "source": "<a href=\"http://twitter.com\" rel=\"nofollow\">Twitter Web Client</a>", "entities": {"urls": [], "hashtags": [], "symbols": [], "user_mentions": [{"screen_name": "tobias31", "indices": [0, 9], "id": 25015718, "id_str": "25015718", "name": "Tobias Harris"}]}, "retweeted": false, "favorited": false, "created_at": "Sat Sep 22 01:54:22 +0000 2012", "id_str": "249325734475214848", "place": null, "in_reply_to_user_id_str": "25015718", "lang": "en", "contributors": null, "text": "@tobias31 Tomorrow night if u in Milwaukee stop thru Club Pulse and check us out... Across the street from the Bradley Center"}