{"user": {"description": "18. LGBT ally. Going through the motions because reasons. Shit happens when I am tired.", "following": false, "profile_image_url": "http://pbs.twimg.com/profile_images/500678362608590849/bBsfKQzJ_normal.jpeg", "verified": false, "listed_count": 9, "location": "Lithuania", "default_profile_image": false, "profile_sidebar_fill_color": "F3F3F3", "time_zone": "Greenland", "id": 57388924, "is_translation_enabled": false, "protected": false, "name": "saulla", "profile_image_url_https": "https://pbs.twimg.com/profile_images/500678362608590849/bBsfKQzJ_normal.jpeg", "profile_sidebar_border_color": "FFFFFF", "profile_background_image_url": "http://pbs.twimg.com/profile_background_images/490454797087027200/-pqNMUbr.jpeg", "geo_enabled": false, "default_profile": false, "profile_background_image_url_https": "https://pbs.twimg.com/profile_background_images/490454797087027200/-pqNMUbr.jpeg", "lang": "en", "is_translator": false, "friends_count": 216, "follow_request_sent": false, "url": "http://t.co/GVnA1v4i48", "profile_link_color": "FF0505", "statuses_count": 16041, "favourites_count": 896, "entities": {"description": {"urls": []}, "url": {"urls": [{"url": "http://t.co/GVnA1v4i48", "display_url": "saulla.tumblr.com", "expanded_url": "http://saulla.tumblr.com", "indices": [0, 22]}]}}, "profile_use_background_image": true, "created_at": "Thu Jul 16 17:22:28 +0000 2009", "profile_background_color": "000000", "profile_background_tile": true, "profile_text_color": "333333", "notifications": false, "utc_offset": -7200, "screen_name": "TheDemonCard", "profile_banner_url": "https://pbs.twimg.com/profile_banners/57388924/1405768371", "contributors_enabled": false, "id_str": "57388924", "followers_count": 745}, "in_reply_to_status_id_str": null, "favorite_count": 0, "retweet_count": 0, "in_reply_to_user_id": null, "id": 249489663750963201, "truncated": false, "in_reply_to_screen_name": null, "coordinates": null, "geo": null, "in_reply_to_status_id": null, "source": "<a href=\"http://twitter.com\" rel=\"nofollow\">Twitter Web Client</a>", "entities": {"urls": [], "hashtags": [], "symbols": [], "user_mentions": []}, "retweeted": false, "favorited": false, "created_at": "Sat Sep 22 12:45:45 +0000 2012", "id_str": "249489663750963201", "place": null, "in_reply_to_user_id_str": null, "lang": "en", "contributors": null, "text": "@4gatha_ I know the feeling. In my country we don't celebrate Halloween too, but we have a Pancake Day in February, so it's the same ;)"}