{"user": {"description": "I am an odd mix of plumber and computer geek, writer and wonder junkie. Co-host of the @HEPodcast.", "following": false, "profile_image_url": "http://pbs.twimg.com/profile_images/440262737537429504/Wo5Ar0jA_normal.jpeg", "verified": false, "listed_count": 20, "location": "Fort Collins, CO", "default_profile_image": false, "profile_sidebar_fill_color": "EFEFEF", "time_zone": "Mountain Time (US & Canada)", "id": 59939938, "is_translation_enabled": false, "protected": false, "name": "Tony Southcotte", "profile_image_url_https": "https://pbs.twimg.com/profile_images/440262737537429504/Wo5Ar0jA_normal.jpeg", "profile_sidebar_border_color": "FFFFFF", "profile_background_image_url": "http://abs.twimg.com/images/themes/theme14/bg.gif", "geo_enabled": false, "default_profile": false, "profile_background_image_url_https": "https://abs.twimg.com/images/themes/theme14/bg.gif", "lang": "en", "is_translator": false, "friends_count": 178, "follow_request_sent": false, "url": "http://t.co/uHEAwv1mQh", "profile_link_color": "009999", "statuses_count": 8368, "favourites_count": 3227, "entities": {"description": {"urls": []}, "url": {"urls": [{"url": "http://t.co/uHEAwv1mQh", "display_url": "humanechoes.com", "expanded_url": "http://humanechoes.com", "indices": [0, 22]}]}}, "profile_use_background_image": true, "created_at": "Sat Jul 25 01:11:57 +0000 2009", "profile_background_color": "131516", "profile_background_tile": true, "profile_text_color": "333333", "notifications": false, "utc_offset": -21600, "screen_name": "tsouthcotte", "profile_banner_url": "https://pbs.twimg.com/profile_banners/59939938/1366764658", "contributors_enabled": false, "id_str": "59939938", "followers_count": 353}, "in_reply_to_status_id_str": null, "favorite_count": 0, "retweet_count": 0, "in_reply_to_user_id": null, "id": 258812092801511424, "truncated": false, "in_reply_to_screen_name": null, "coordinates": null, "geo": null, "in_reply_to_status_id": null, "source": "<a href=\"https://about.twitter.com/products/tweetdeck\" rel=\"nofollow\">TweetDeck</a>", "entities": {"urls": [], "hashtags": [], "symbols": [], "user_mentions": []}, "retweeted": false, "favorited": false, "created_at": "Thu Oct 18 06:09:46 +0000 2012", "id_str": "258812092801511424", "place": null, "in_reply_to_user_id_str": null, "lang": "en", "contributors": null, "text": "You know what? Goon may be a low brow comedy, but it was fun as hell. Go netflix it."}