{"user": {"description": "Arbonne International Independent Consultant", "following": false, "profile_image_url": "http://pbs.twimg.com/profile_images/509180112886308864/GD95B_t2_normal.jpeg", "verified": false, "listed_count": 0, "location": "", "default_profile_image": false, "profile_sidebar_fill_color": "EADEAA", "time_zone": "Quito", "id": 344412167, "is_translation_enabled": false, "protected": false, "name": "Jayla Hyde", "profile_image_url_https": "https://pbs.twimg.com/profile_images/509180112886308864/GD95B_t2_normal.jpeg", "profile_sidebar_border_color": "D9B17E", "profile_background_image_url": "http://abs.twimg.com/images/themes/theme8/bg.gif", "geo_enabled": false, "default_profile": false, "profile_background_image_url_https": "https://abs.twimg.com/images/themes/theme8/bg.gif", "lang": "en", "is_translator": false, "friends_count": 622, "follow_request_sent": false, "url": null, "profile_link_color": "9D582E", "statuses_count": 1487, "favourites_count": 1390, "entities": {"description": {"urls": []}}, "profile_use_background_image": true, "created_at": "Fri Jul 29 01:14:44 +0000 2011", "profile_background_color": "8B542B", "profile_background_tile": false, "profile_text_color": "333333", "notifications": false, "utc_offset": -18000, "screen_name": "Jayla_Hyde", "profile_banner_url": "https://pbs.twimg.com/profile_banners/344412167/1410232977", "contributors_enabled": false, "id_str": "344412167", "followers_count": 149}, "in_reply_to_status_id_str": "261279500900397057", "favorite_count": 1, "retweet_count": 0, "in_reply_to_user_id": 57868879, "id": 261282355954733056, "truncated": false, "in_reply_to_screen_name": "PatMessenger", "coordinates": null, "geo": null, "in_reply_to_status_id": 261279500900397057, "source": "<a href=\"http://twitter.com/download/iphone\" rel=\"nofollow\">Twitter for iPhone</a>", "entities": {"urls": [], "hashtags": [], "symbols": [], "user_mentions": [{"screen_name": "PatMessenger", "indices": [0, 13], "id": 57868879, "id_str": "57868879", "name": "Patrick Messenger"}]}, "retweeted": false, "favorited": false, "created_at": "Thu Oct 25 01:45:42 +0000 2012", "id_str": "261282355954733056", "place": null, "in_reply_to_user_id_str": "57868879", "lang": "en", "contributors": null, "text": "@PatMessenger great choices!!! I went to Olympic park too, but if you're just there for the weekend, that may be pushin it!"}