{"user": {"description": "Published Nikon User. Regional fundraiser for Vulcan to the Sky Club @VulcanSCentral,  volunteer at Farnborough Aviation & Science Trust https://t.co/V28oyCPA5G", "following": false, "profile_image_url": "http://pbs.twimg.com/profile_images/512668359297867777/JYitlI9h_normal.jpeg", "verified": false, "listed_count": 21, "location": "Yateley, Hants ", "default_profile_image": false, "profile_sidebar_fill_color": "C1CFD8", "time_zone": "London", "id": 306647135, "is_translation_enabled": false, "protected": false, "name": "\u2708\u2708 Jo  Ayres \u2708\u2708", "profile_image_url_https": "https://pbs.twimg.com/profile_images/512668359297867777/JYitlI9h_normal.jpeg", "profile_sidebar_border_color": "000000", "profile_background_image_url": "http://pbs.twimg.com/profile_background_images/841554344/8d726871b97472b51ab9c06efcb2ecda.jpeg", "geo_enabled": true, "default_profile": false, "profile_background_image_url_https": "https://pbs.twimg.com/profile_background_images/841554344/8d726871b97472b51ab9c06efcb2ecda.jpeg", "lang": "en", "is_translator": false, "friends_count": 1851, "follow_request_sent": false, "url": null, "profile_link_color": "655850", "statuses_count": 31972, "favourites_count": 23023, "entities": {"description": {"urls": [{"url": "https://t.co/V28oyCPA5G", "display_url": "flickr.com", "expanded_url": "https://www.flickr.com", "indices": [137, 160]}]}}, "profile_use_background_image": true, "created_at": "Sat May 28 07:06:35 +0000 2011", "profile_background_color": "50433B", "profile_background_tile": false, "profile_text_color": "A3A4A8", "notifications": false, "utc_offset": 3600, "screen_name": "Ayresjo", "profile_banner_url": "https://pbs.twimg.com/profile_banners/306647135/1411157022", "contributors_enabled": false, "id_str": "306647135", "followers_count": 1792}, "in_reply_to_status_id_str": "262114563867160577", "favorite_count": 0, "retweet_count": 0, "in_reply_to_user_id": 20782091, "id": 262115068320284672, "truncated": false, "in_reply_to_screen_name": "Aerostatpilot", "coordinates": null, "geo": null, "in_reply_to_status_id": 262114563867160577, "source": "<a href=\"http://twitter.com/download/iphone\" rel=\"nofollow\">Twitter for iPhone</a>", "entities": {"urls": [], "hashtags": [], "symbols": [], "user_mentions": [{"screen_name": "apgphoto", "indices": [0, 9], "id": 444192423, "id_str": "444192423", "name": "Andrew P Gibson"}]}, "retweeted": false, "favorited": false, "created_at": "Sat Oct 27 08:54:36 +0000 2012", "id_str": "262115068320284672", "place": null, "in_reply_to_user_id_str": "20782091", "lang": "en", "contributors": null, "text": "@APGPhoto oooh nice .. Tis tempting to go up the lakes with my Nikon ... \nHmmmm I may do that .."}