{"user": {"description": "happy-go-lucky \u2022 adventure-seeker \u2022 cheese-lover \u2022 disneyphile \u2022 bookworm \u2022 born on the third of november", "following": false, "profile_image_url": "http://pbs.twimg.com/profile_images/2951086496/cd6f056b82c52fd5d6f331656bbe0bfb_normal.jpeg", "verified": false, "listed_count": 1, "location": "Philippines", "default_profile_image": false, "profile_sidebar_fill_color": "95E8EC", "time_zone": "Hong Kong", "id": 185101254, "is_translation_enabled": false, "protected": false, "name": "Kevin Garon", "profile_image_url_https": "https://pbs.twimg.com/profile_images/2951086496/cd6f056b82c52fd5d6f331656bbe0bfb_normal.jpeg", "profile_sidebar_border_color": "FFFFFF", "profile_background_image_url": "http://pbs.twimg.com/profile_background_images/496211935172386817/YRMbPc_J.jpeg", "geo_enabled": true, "default_profile": false, "profile_background_image_url_https": "https://pbs.twimg.com/profile_background_images/496211935172386817/YRMbPc_J.jpeg", "lang": "en", "is_translator": false, "friends_count": 722, "follow_request_sent": false, "url": "http://t.co/lF792rLLrY", "profile_link_color": "0099B9", "statuses_count": 9162, "favourites_count": 16, "entities": {"description": {"urls": []}, "url": {"urls": [{"url": "http://t.co/lF792rLLrY", "display_url": "instagram.com/kevingaron", "expanded_url": "http://instagram.com/kevingaron", "indices": [0, 22]}]}}, "profile_use_background_image": true, "created_at": "Tue Aug 31 06:38:50 +0000 2010", "profile_background_color": "0099B9", "profile_background_tile": true, "profile_text_color": "3C3940", "notifications": false, "utc_offset": 28800, "screen_name": "kevingaron", "profile_banner_url": "https://pbs.twimg.com/profile_banners/185101254/1410233478", "contributors_enabled": false, "id_str": "185101254", "followers_count": 145}, "in_reply_to_status_id_str": "262203077308841984", "favorite_count": 0, "retweet_count": 0, "in_reply_to_user_id": 22716000, "id": 262206571201822721, "truncated": false, "in_reply_to_screen_name": "ariaclemente", "coordinates": null, "geo": null, "in_reply_to_status_id": 262203077308841984, "source": "<a href=\"http://twitter.com\" rel=\"nofollow\">Twitter Web Client</a>", "entities": {"urls": [], "hashtags": [], "symbols": [], "user_mentions": [{"screen_name": "ariaclemente", "indices": [0, 13], "id": 22716000, "id_str": "22716000", "name": "Aria Clemente"}, {"screen_name": "camphalfblood", "indices": [124, 138], "id": 19031819, "id_str": "19031819", "name": "Rick Riordan"}]}, "retweeted": false, "favorited": false, "created_at": "Sat Oct 27 14:58:12 +0000 2012", "id_str": "262206571201822721", "place": null, "in_reply_to_user_id_str": "22716000", "lang": "en", "contributors": null, "text": "@ariaclemente Wow! you're also a percy jackson fan! :-) The 4th book of Heroes of Olympus will be entitled \"House of Hades\" @camphalfblood"}