{"user": {"description": "Manager, Baby Girl Fresh. Rappers/Singers/Dancers...They PUT ON A SHOW! No sleeping on ya girls we'll wake you up...No Slumber", "following": false, "profile_image_url": "http://pbs.twimg.com/profile_images/378800000128286823/6fff116cf6867312764bd243b9de41b8_normal.jpeg", "verified": false, "listed_count": 1, "location": "Dallas, TX", "default_profile_image": false, "profile_sidebar_fill_color": "CCDB98", "time_zone": null, "id": 832499923, "is_translation_enabled": false, "protected": false, "name": "Baby Girl Fresh ", "profile_image_url_https": "https://pbs.twimg.com/profile_images/378800000128286823/6fff116cf6867312764bd243b9de41b8_normal.jpeg", "profile_sidebar_border_color": "000000", "profile_background_image_url": "http://pbs.twimg.com/profile_background_images/723342844/4f9633c9712d262819d5002eeeeaa0b5.jpeg", "geo_enabled": false, "default_profile": false, "profile_background_image_url_https": "https://pbs.twimg.com/profile_background_images/723342844/4f9633c9712d262819d5002eeeeaa0b5.jpeg", "lang": "en", "is_translator": false, "friends_count": 418, "follow_request_sent": false, "url": "http://t.co/Wn55vkJMEf", "profile_link_color": "0084B4", "statuses_count": 1657, "favourites_count": 38, "entities": {"description": {"urls": []}, "url": {"urls": [{"url": "http://t.co/Wn55vkJMEf", "display_url": "babygirlfresh.com", "expanded_url": "http://www.babygirlfresh.com", "indices": [0, 22]}]}}, "profile_use_background_image": true, "created_at": "Wed Sep 19 03:52:51 +0000 2012", "profile_background_color": "022330", "profile_background_tile": true, "profile_text_color": "E2947C", "notifications": false, "utc_offset": null, "screen_name": "ImBabyGirlFresh", "profile_banner_url": "https://pbs.twimg.com/profile_banners/832499923/1373720212", "contributors_enabled": false, "id_str": "832499923", "followers_count": 189}, "in_reply_to_status_id_str": null, "favorite_count": 0, "retweet_count": 0, "in_reply_to_user_id": null, "id": 263085638113431552, "truncated": false, "possibly_sensitive": false, "in_reply_to_screen_name": null, "coordinates": null, "geo": null, "in_reply_to_status_id": null, "source": "<a href=\"http://twitter.com\" rel=\"nofollow\">Twitter Web Client</a>", "entities": {"urls": [{"url": "http://t.co/5D1UBeLB", "display_url": "babygirlfresh.com", "expanded_url": "http://www.babygirlfresh.com", "indices": [108, 128]}], "hashtags": [], "symbols": [], "user_mentions": []}, "retweeted": false, "favorited": false, "created_at": "Tue Oct 30 01:11:18 +0000 2012", "id_str": "263085638113431552", "place": null, "in_reply_to_user_id_str": null, "lang": "en", "contributors": null, "text": "AYYYYYE!!! Baby Girl Fresh will be at the HOUSE OF BLUES in December! Make sure yall come out and SUPPORT!  http://t.co/5D1UBeLB"}