{"user": {"description": "Tweets about breaking news, weather, sports, Oklahoma culture and trending topics. All brought to you by the team at http://t.co/wUNuArr8Zf and The Oklahoman.", "following": false, "profile_image_url": "http://pbs.twimg.com/profile_images/435982275/NewsOk_Icon_normal.png", "verified": false, "listed_count": 998, "location": "Oklahoma City, OK", "default_profile_image": false, "profile_sidebar_fill_color": "C4C4C4", "time_zone": "Central Time (US & Canada)", "id": 7406262, "is_translation_enabled": false, "protected": false, "name": "NewsOK", "profile_image_url_https": "https://pbs.twimg.com/profile_images/435982275/NewsOk_Icon_normal.png", "profile_sidebar_border_color": "59A3C2", "profile_background_image_url": "http://pbs.twimg.com/profile_background_images/40011013/Background.png", "geo_enabled": true, "default_profile": false, "profile_background_image_url_https": "https://pbs.twimg.com/profile_background_images/40011013/Background.png", "lang": "en", "is_translator": false, "friends_count": 319, "follow_request_sent": false, "url": "http://t.co/SzsIFRJBN7", "profile_link_color": "000000", "statuses_count": 43877, "favourites_count": 69, "entities": {"description": {"urls": [{"url": "http://t.co/wUNuArr8Zf", "display_url": "NewsOK.com", "expanded_url": "http://NewsOK.com", "indices": [117, 139]}]}, "url": {"urls": [{"url": "http://t.co/SzsIFRJBN7", "display_url": "newsok.com", "expanded_url": "http://newsok.com", "indices": [0, 22]}]}}, "profile_use_background_image": true, "created_at": "Wed Jul 11 16:47:34 +0000 2007", "profile_background_color": "FFFFFF", "profile_background_tile": false, "profile_text_color": "4A4444", "notifications": false, "utc_offset": -18000, "screen_name": "NewsOK", "contributors_enabled": false, "id_str": "7406262", "followers_count": 39630}, "in_reply_to_status_id_str": null, "favorite_count": 0, "retweet_count": 2, "in_reply_to_user_id": null, "id": 263339692605460480, "truncated": false, "possibly_sensitive": false, "in_reply_to_screen_name": null, "coordinates": null, "geo": null, "in_reply_to_status_id": null, "source": "<a href=\"http://twitter.com\" rel=\"nofollow\">Twitter Web Client</a>", "entities": {"urls": [{"url": "http://t.co/XzXF6N86", "display_url": "facebook.com/events/4363817\u2026", "expanded_url": "http://www.facebook.com/events/436381766419326/", "indices": [107, 127]}], "hashtags": [], "symbols": [], "user_mentions": []}, "retweeted": false, "favorited": false, "created_at": "Tue Oct 30 18:00:49 +0000 2012", "id_str": "263339692605460480", "place": null, "in_reply_to_user_id_str": null, "lang": "en", "contributors": null, "text": "Tune in at 2 p.m. tomorrow for a Google+ Hangout with our political reporters to discuss the 2012 election http://t.co/XzXF6N86"}