{"user": {"description": "Love My Bae And My Little One \u2764\ufe0f", "following": false, "profile_image_url": "http://pbs.twimg.com/profile_images/496957325115412481/c0HnCI8o_normal.jpeg", "verified": false, "listed_count": 0, "location": "", "default_profile_image": false, "profile_sidebar_fill_color": "DDEEF6", "time_zone": "Eastern Time (US & Canada)", "id": 428841738, "is_translation_enabled": false, "protected": false, "name": "Waiinemac ", "profile_image_url_https": "https://pbs.twimg.com/profile_images/496957325115412481/c0HnCI8o_normal.jpeg", "profile_sidebar_border_color": "C0DEED", "profile_background_image_url": "http://abs.twimg.com/images/themes/theme1/bg.png", "geo_enabled": false, "default_profile": true, "profile_background_image_url_https": "https://abs.twimg.com/images/themes/theme1/bg.png", "lang": "en", "is_translator": false, "friends_count": 241, "follow_request_sent": false, "url": null, "profile_link_color": "0084B4", "statuses_count": 18288, "favourites_count": 641, "entities": {"description": {"urls": []}}, "profile_use_background_image": true, "created_at": "Mon Dec 05 07:31:35 +0000 2011", "profile_background_color": "C0DEED", "profile_background_tile": false, "profile_text_color": "333333", "notifications": false, "utc_offset": -14400, "screen_name": "WaiineMac", "profile_banner_url": "https://pbs.twimg.com/profile_banners/428841738/1407319738", "contributors_enabled": false, "id_str": "428841738", "followers_count": 451}, "in_reply_to_status_id_str": null, "favorite_count": 0, "retweet_count": 0, "in_reply_to_user_id": null, "id": 263867263474597888, "truncated": false, "in_reply_to_screen_name": null, "coordinates": null, "geo": null, "in_reply_to_status_id": null, "source": "<a href=\"http://twitter.com/download/iphone\" rel=\"nofollow\">Twitter for iPhone</a>", "entities": {"urls": [], "hashtags": [], "symbols": [], "user_mentions": []}, "retweeted": false, "favorited": false, "created_at": "Thu Nov 01 04:57:12 +0000 2012", "id_str": "263867263474597888", "place": null, "in_reply_to_user_id_str": null, "lang": "en", "contributors": null, "text": "Niggas be on the LAKERS DICK...we still gon finish damn near first seed...while yo team be struggling for the 8th spot"}