{"user": {"description": ";*\u260513 yrs old...For every one who would l.u.v. 2 follow me3\u25a1\u25a1\u25c7\u2606| I'm very very sweet3!| I L.U.V. \u00fc All!! \r\nI just need to trust u all!;)", "following": false, "profile_image_url": "http://pbs.twimg.com/profile_images/3440507846/9b7af52c025d7097f2ad1892ff0f9f26_normal.jpeg", "verified": false, "listed_count": 0, "location": "NY", "default_profile_image": false, "profile_sidebar_fill_color": "DDEEF6", "time_zone": "Hawaii", "id": 709707654, "is_translation_enabled": false, "protected": false, "name": "MaryL\u00fcvsLife\u25a1\u25a1", "profile_image_url_https": "https://pbs.twimg.com/profile_images/3440507846/9b7af52c025d7097f2ad1892ff0f9f26_normal.jpeg", "profile_sidebar_border_color": "C0DEED", "profile_background_image_url": "http://abs.twimg.com/images/themes/theme1/bg.png", "geo_enabled": true, "default_profile": true, "profile_background_image_url_https": "https://abs.twimg.com/images/themes/theme1/bg.png", "lang": "en", "is_translator": false, "friends_count": 456, "follow_request_sent": false, "url": null, "profile_link_color": "0084B4", "statuses_count": 2316, "favourites_count": 155, "entities": {"description": {"urls": []}}, "profile_use_background_image": true, "created_at": "Sat Jul 21 22:56:31 +0000 2012", "profile_background_color": "C0DEED", "profile_background_tile": false, "profile_text_color": "333333", "notifications": false, "utc_offset": -36000, "screen_name": "Princess_Mary41", "profile_banner_url": "https://pbs.twimg.com/profile_banners/709707654/1364531071", "contributors_enabled": false, "id_str": "709707654", "followers_count": 69}, "in_reply_to_status_id_str": null, "favorite_count": 0, "retweet_count": 0, "in_reply_to_user_id": null, "id": 263825795636686849, "truncated": false, "in_reply_to_screen_name": null, "coordinates": null, "geo": null, "in_reply_to_status_id": null, "source": "<a href=\"http://mobile.twitter.com\" rel=\"nofollow\">Mobile Web</a>", "entities": {"urls": [], "hashtags": [], "symbols": [], "user_mentions": []}, "retweeted": false, "favorited": false, "created_at": "Thu Nov 01 02:12:25 +0000 2012", "id_str": "263825795636686849", "place": null, "in_reply_to_user_id_str": null, "lang": "en", "contributors": null, "text": "Bad Girls Club: Mexico...is so official now meaning most of the girls going off on each other. I can't wait until monday.  |D"}