{"user": {"description": "University of California Berkeley Class of 2018", "following": false, "profile_image_url": "http://pbs.twimg.com/profile_images/433513588888584192/UrmHxSMy_normal.jpeg", "verified": false, "listed_count": 12, "location": "Vancouver, BC", "default_profile_image": false, "profile_sidebar_fill_color": "DDEEF6", "time_zone": null, "id": 607803479, "is_translation_enabled": false, "protected": false, "name": "Noemie Thomas", "profile_image_url_https": "https://pbs.twimg.com/profile_images/433513588888584192/UrmHxSMy_normal.jpeg", "profile_sidebar_border_color": "C0DEED", "profile_background_image_url": "http://abs.twimg.com/images/themes/theme1/bg.png", "geo_enabled": true, "default_profile": true, "profile_background_image_url_https": "https://abs.twimg.com/images/themes/theme1/bg.png", "lang": "en", "is_translator": false, "friends_count": 402, "follow_request_sent": false, "url": null, "profile_link_color": "0084B4", "statuses_count": 1071, "favourites_count": 630, "entities": {"description": {"urls": []}}, "profile_use_background_image": true, "created_at": "Thu Jun 14 04:09:14 +0000 2012", "profile_background_color": "C0DEED", "profile_background_tile": false, "profile_text_color": "333333", "notifications": false, "utc_offset": null, "screen_name": "noemie_thomas", "profile_banner_url": "https://pbs.twimg.com/profile_banners/607803479/1392192757", "contributors_enabled": false, "id_str": "607803479", "followers_count": 377}, "in_reply_to_status_id_str": null, "favorite_count": 0, "retweet_count": 1, "in_reply_to_user_id": null, "id": 264228104954855425, "truncated": false, "in_reply_to_screen_name": null, "coordinates": null, "geo": null, "in_reply_to_status_id": null, "source": "<a href=\"http://twitter.com/download/iphone\" rel=\"nofollow\">Twitter for iPhone</a>", "entities": {"urls": [], "hashtags": [{"indices": [92, 101], "text": "altitude"}, {"indices": [102, 109], "text": "paceit"}], "symbols": [], "user_mentions": []}, "retweeted": false, "favorited": false, "created_at": "Fri Nov 02 04:51:04 +0000 2012", "id_str": "264228104954855425", "place": null, "in_reply_to_user_id_str": null, "lang": "en", "contributors": null, "text": "Calgary tomorrow for the first meet of the season! Can't wait to get some early racing done #altitude #paceit"}