{"user": {"description": "Close your eyes and enjoy the roller coaster :D     ~Saw 1D in Dusseldorf 02.07.14 *-* ~   \u2022 0/12\u2022  \u20220/5\u2022", "following": false, "profile_image_url": "http://pbs.twimg.com/profile_images/508174575855992833/gmViFd9t_normal.jpeg", "verified": false, "listed_count": 4, "location": "Germany/London", "default_profile_image": false, "profile_sidebar_fill_color": "95E8EC", "time_zone": "Athens", "id": 798029714, "is_translation_enabled": false, "protected": false, "name": "Diana Horlik", "profile_image_url_https": "https://pbs.twimg.com/profile_images/508174575855992833/gmViFd9t_normal.jpeg", "profile_sidebar_border_color": "FFFFFF", "profile_background_image_url": "http://pbs.twimg.com/profile_background_images/378800000023519864/86bd412c10ab3131dc65b2901aff92c6.jpeg", "geo_enabled": true, "default_profile": false, "profile_background_image_url_https": "https://pbs.twimg.com/profile_background_images/378800000023519864/86bd412c10ab3131dc65b2901aff92c6.jpeg", "lang": "de", "is_translator": false, "friends_count": 37, "follow_request_sent": false, "url": null, "profile_link_color": "0099B9", "statuses_count": 7994, "favourites_count": 32, "entities": {"description": {"urls": []}}, "profile_use_background_image": true, "created_at": "Sun Sep 02 10:59:51 +0000 2012", "profile_background_color": "0099B9", "profile_background_tile": true, "profile_text_color": "3C3940", "notifications": false, "utc_offset": 10800, "screen_name": "Diana73666", "profile_banner_url": "https://pbs.twimg.com/profile_banners/798029714/1380209658", "contributors_enabled": false, "id_str": "798029714", "followers_count": 675}, "in_reply_to_status_id_str": null, "favorite_count": 0, "retweet_count": 0, "in_reply_to_user_id": 29898542, "id": 264246162444402688, "truncated": false, "in_reply_to_screen_name": "HeffronDrive", "coordinates": null, "geo": null, "in_reply_to_status_id": null, "source": "<a href=\"http://twitter.com/download/android\" rel=\"nofollow\">Twitter for Android</a>", "entities": {"urls": [], "hashtags": [], "symbols": [], "user_mentions": [{"screen_name": "HeffronDrive", "indices": [0, 13], "id": 29898542, "id_str": "29898542", "name": "Kendall Schmidt"}]}, "retweeted": false, "favorited": false, "created_at": "Fri Nov 02 06:02:49 +0000 2012", "id_str": "264246162444402688", "place": null, "in_reply_to_user_id_str": "29898542", "lang": "en", "contributors": null, "text": "@HeffronDrive Congratulations Kendall in Germany it is 7 clock Friday November 2, so Happy B-day"}